simple_chatbot_lib/chatbots.py
simple_chatbot_lib/context_services.py
simple_chatbot_lib/mappers.py
simple_chatbot_lib/core/models.py
simple_chatbot_lib/third_parties/context_services.py
simple_chatbot_lib-0.1.6.dist-info/LICENSE
simple_chatbot_lib-0.1.6.dist-info/METADATA
simple_chatbot_lib-0.1.6.dist-info/WHEEL
simple_chatbot_lib-0.1.6.dist-info/top_level.txt
simple_chatbot_lib-0.1.6.dist-info/RECORD
