Metadata-Version: 2.1
Name: simple_chatbot_lib
Version: 0.1.6
Summary: A simple package for create chatbots using LangChain
Author-email: Gabriel Pinto Sasaki <gabrielpintosasaki@outlook.com>
License: GNU GENERAL PUBLIC LICENSE
Project-URL: Repository, https://github.com/Gabriel-Sasaki/chatbot-lib
Project-URL: Issues, https://github.com/Gabriel-Sasaki/chatbot-lib/issues
Classifier: Programming Language :: Python :: 3.11
Classifier: License :: OSI Approved :: GNU General Public License v3 (GPLv3)
Classifier: Operating System :: OS Independent
Requires-Python: >=3.11
License-File: LICENSE
Requires-Dist: langchain >=0.2.12
Provides-Extra: azure
Requires-Dist: azure-search-documents >=11.5.1 ; extra == 'azure'
Requires-Dist: azure-common >=1.1.28 ; extra == 'azure'
Requires-Dist: azure-core >=1.30.2 ; extra == 'azure'
